evi/__init__.py
evi-0.0.2.dist-info/METADATA
evi-0.0.2.dist-info/WHEEL
evi-0.0.2.dist-info/top_level.txt
evi-0.0.2.dist-info/RECORD
