Metadata-Version: 2.1
Name: evi
Version: 0.0.2
Summary: Implementation  of DS theory (D-S evidence theory)
Home-page: https://github.com/qiaokuoyuan/evi
Author: qiaokuoyuan
Author-email: 457361577@qq.com
License: BSD License
Platform: all
Classifier: Programming Language :: Python :: 3
Classifier: License :: OSI Approved :: MIT License
Classifier: Operating System :: OS Independent
Requires-Python: >=3.6
